chaineripy/__init__.py
chaineripy/extensions/__init__.py
chaineripy/extensions/print_report.py
chaineripy/extensions/progress_bar.py
chaineripy-0.1.1.dist-info/DESCRIPTION.rst
chaineripy-0.1.1.dist-info/METADATA
chaineripy-0.1.1.dist-info/RECORD
chaineripy-0.1.1.dist-info/WHEEL
chaineripy-0.1.1.dist-info/metadata.json
chaineripy-0.1.1.dist-info/top_level.txt
